{"cameraMode":{"drawMode":0,"name":"Shaded","section":"Shading Mode"},"sceneLighting":true,"audioPlay":false,"sceneViewState":{"m_AlwaysRefresh":false,"showFog":true,"showSkybox":true,"showFlares":true,"showImageEffects":true,"showParticleSystems":true,"showVisualEffectGraphs":true,"m_FxEnabled":true},"in2DMode":false,"pivot":{"x":11.856325149536133,"y":9.827335357666016,"z":18.28133201599121},"rotation":{"x":-0.16557559370994569,"y":0.7646031975746155,"z":-0.21681280434131623,"w":-0.5839122533798218},"size":10.0,"orthographic":false}